lfview/__init__.py
lfview/resources/__init__.py
lfview/resources/files/__init__.py
lfview/resources/files/base.py
lfview/resources/files/files.py
lfview_resources_files-0.0.2.dist-info/METADATA
lfview_resources_files-0.0.2.dist-info/WHEEL
lfview_resources_files-0.0.2.dist-info/top_level.txt
lfview_resources_files-0.0.2.dist-info/RECORD
