Metadata-Version: 2.1
Name: lfview-resources-files
Version: 0.0.2
Summary: Definitions and documentation for LF View file resources
Home-page: https://lfview.com
Author: Seequent
Author-email: franklin.koch@seequent.com
License: MIT
Download-URL: https://github.com/seequent/lfview-resources-files
Platform: Windows
Platform: Linux
Platform: Solaris
Platform: Mac OS-X
Platform: Unix
Classifier: Development Status :: 4 - Beta
Classifier: Programming Language :: Python :: 2.7
Classifier: Programming Language :: Python :: 3.6
Classifier: License :: OSI Approved :: MIT License
Classifier: Topic :: Scientific/Engineering
Classifier: Operating System :: Microsoft :: Windows
Classifier: Operating System :: POSIX
Classifier: Operating System :: Unix
Classifier: Operating System :: MacOS
Classifier: Natural Language :: English
Requires-Dist: properties[full] (>=0.5.6)
